phony/__init__.py
phony/pipeline.py
phony/scorer.py
phony/tokens.py
phony/training.py
spacy_phony-0.1.0.dist-info/LICENSE
spacy_phony-0.1.0.dist-info/METADATA
spacy_phony-0.1.0.dist-info/WHEEL
spacy_phony-0.1.0.dist-info/entry_points.txt
spacy_phony-0.1.0.dist-info/top_level.txt
spacy_phony-0.1.0.dist-info/RECORD
